FineST/SparseAEH.py
FineST/SpatialDM.py
FineST/__init__.py
FineST/celltype.py
FineST/cropping.py
FineST/downstream.py
FineST/evaluation.py
FineST/inference.py
FineST/loadData.py
FineST/model.py
FineST/plottings.py
FineST/processData.py
FineST/train.py
FineST/traintest.py
FineST/utils.py
FineST/version.py
FineST/datasets/__init__.py
FineST/datasets/_util_dataset.py
FineST/datasets/dataset.py
FineSTtest/NB_module.py
FineSTtest/SparseAEH.py
FineSTtest/SpatialDM.py
FineSTtest/__init__.py
FineSTtest/celltype.py
FineSTtest/cropping.py
FineSTtest/evaluation.py
FineSTtest/inference.py
FineSTtest/loadData.py
FineSTtest/loss.py
FineSTtest/model.py
FineSTtest/plottings.py
FineSTtest/processData.py
FineSTtest/train.py
FineSTtest/utils.py
FineSTtest/version.py
FineSTtest/datasets/__init__.py
FineSTtest/datasets/_util_dataset.py
FineSTtest/datasets/dataset.py
FineST-0.1.2.dist-info/LICENSE
FineST-0.1.2.dist-info/METADATA
FineST-0.1.2.dist-info/WHEEL
FineST-0.1.2.dist-info/top_level.txt
FineST-0.1.2.dist-info/RECORD
