Metadata-Version: 2.1
Name: FineST
Version: 0.1.2
Summary: FineST: Fine-grained Spatial Transcriptomic
Home-page: https://github.com/LingyuLi-math/FineST
Author: ['Lingyu Li', 'Yuanhua Huang']
Author-email: lingyuli@hku.hk
License: Apache-2.0
Keywords: Spatial transcriptomics,HE stained images,Cell-cell communication,Ligand-recptor interaction
License-File: LICENSE
Requires-Dist: anndata ==0.9.2
Requires-Dist: scanpy ==1.9.8
Requires-Dist: SpatialDE
Requires-Dist: SpatialDM ==0.2.0
Requires-Dist: SparseAEH ==0.1.0
Requires-Dist: pyarrow ==17.0.0
Requires-Dist: pykdtree ==1.3.7
Requires-Dist: scikit-image
Requires-Dist: numpy >=1.9.0
Requires-Dist: scipy >=1.4.0
Requires-Dist: statsmodels >=0.11
Requires-Dist: pandas ==2.0.3
Requires-Dist: h5py ==3.10.0
Requires-Dist: openpyxl ==3.1.5
Requires-Dist: brokenaxes ==0.6.2
Requires-Dist: pyreadr ==0.5.2
Requires-Dist: squidpy ==1.2.3
Requires-Dist: stardist ==0.9.1
Requires-Dist: tensorflow ==2.13.1
Requires-Dist: transpa ==0.1.1
Requires-Dist: matplotlib >=3.1.2
Requires-Dist: holoviews
Requires-Dist: seaborn ==0.13.2
Requires-Dist: selenium
Requires-Dist: plotly ==5.24.1
Requires-Dist: tenacity ==9.0.0
Requires-Dist: nbformat ==5.10.4
Requires-Dist: kaleido ==0.2.1
Requires-Dist: numpy
Requires-Dist: scikit-learn >=0.23
Requires-Dist: hilearn
Requires-Dist: threadpoolctl
Requires-Dist: tqdm
Provides-Extra: docs
Requires-Dist: sphinx-bootstrap-theme ; extra == 'docs'
